extrablox/__init__.py
extrablox/core/__init__.py
extrablox/core/client.py
extra_blox-1.dist-info/METADATA
extra_blox-1.dist-info/WHEEL
extra_blox-1.dist-info/licenses/LICENSE
extra_blox-1.dist-info/RECORD
