Metadata-Version: 2.4
Name: extra.blox
Version: 1
Summary: A Python library for interacting with Roblox's API asynchronously .
Project-URL: Homepage, https://github.com/markination/extra.blox
Project-URL: Issues, https://github.com/markination/extra.blox/issues
Author-email: "mark.api" <me@markapi.tech>
License-Expression: MIT
License-File: LICENSE
Classifier: Operating System :: OS Independent
Classifier: Programming Language :: Python :: 3
Requires-Python: >=3.9
Requires-Dist: httpx>=0.24.0
